pydiscrape/__init__.py
pydiscrape-0.0.1.dist-info/WHEEL
pydiscrape-0.0.1.dist-info/METADATA
pydiscrape-0.0.1.dist-info/RECORD
